{"_type":"export","__export_format":4,"__export_date":"2022-12-08T13:51:47.250Z","__export_source":"insomnia.desktop.app:v2022.6.0","resources":[{"_id":"req_b0ed1b3e2602488c80b525cd9f9bce2d","parentId":"fld_05f619cd6e3a4ae08db8c167cdb82bd0","modified":1670496758863,"created":1669904971069,"url":"{{ _.BASE_URL }}/users","name":"Criar usuário","description":"### Todos os campos de envio são obrigatórios\n- fullname - deve ser do tipo string\n- username - deve ser do tipo string\n- password - deve ser do tipo string\n- emails - deve ser um array de strings\n- phones - deve ser um array de strings\n\n#### Essa rota é liberada a todos\n\n### Retorno esperado\n**STATUS 201 Created**\n```json\n{\n\t\"createdAt\": \"2022-12-08T09:21:38.137Z\",\n\t\"updatedAt\": \"2022-12-08T09:21:38.137Z\",\n\t\"id\": \"0cec3afc-b3b3-4158-a0cf-b38bdc512371\",\n\t\"fullname\": \"Bruno Tibério Santinoni\",\n\t\"username\": \"bruno\",\n\t\"emails\": [\n\t\t\"email1@gmail.com\",\n\t\t\"email2@gmail.com\"\n\t],\n\t\"phones\": [\n\t\t\"61999999999\",\n\t\t\"61955555555\"\n\t]\n}\n```","method":"POST","body":{"mimeType":"application/json","text":"{\n\t\"fullname\": \"Bruno Tibério Santinoni\",\n\t\"username\": \"bruno\",\n\t\"password\": \"1234\", \n\t\"emails\": [\"email1@gmail.com\", \"email2@gmail.com\"], \n\t\"phones\": [\"61999999999\", \"61955555555\"]\n}"},"parameters":[],"headers":[{"name":"Content-Type","value":"application/json"}],"authentication":{},"metaSortKey":-1669507599791,"isPrivate":false,"settingStoreCookies":true,"settingSendCookies":true,"settingDisableRenderRequestBody":false,"settingEncodeUrl":true,"settingRebuildPath":true,"settingFollowRedirects":"global","_type":"request"},{"_id":"fld_05f619cd6e3a4ae08db8c167cdb82bd0","parentId":"wrk_fe269e2b2b2f4b49a48b1a140f511443","modified":1670493475608,"created":1669902647880,"name":"Usuários","description":"<p>Rota responsável por criar, listar, atualizar e deletar usuários do sistema<p>","environment":{},"environmentPropertyOrder":null,"metaSortKey":-1669902687480,"_type":"request_group"},{"_id":"wrk_fe269e2b2b2f4b49a48b1a140f511443","parentId":null,"modified":1670493366542,"created":1669902565622,"name":"Agenda - Fullstack Teste Técnico M6","description":"<h1>Uma solução para seus agendamentos</h1>\n<ul>Acesse os repositórios e deploy\n\t<li>\n\t\t<a href=\"https://github.com/brunotiberio/s3-fullstack-teste-frontend-brunotiberio\" target=\"_blank\">Repositório Frontend</a>\n\t</li>\n\t<li>\n\t\t<a href=\"https://agenda-teste-tecnico.vercel.app/\" target=\"_blank\">Deploy Frontend</a>\n\t</li>\n\t<li>\n\t\t<a href=\"https://github.com/brunotiberio/s3-fullstack-teste-backend-brunotiberio\" target=\"_blank\">Repositório Backend</a>\n\t</li>\n</ul>","scope":"collection","_type":"workspace"},{"_id":"req_9c40208a096946fd9b600de265544917","parentId":"fld_05f619cd6e3a4ae08db8c167cdb82bd0","modified":1670494317487,"created":1669923917572,"url":"{{ _.BASE_URL }}/users","name":"Criar usuário - Username já existe","description":"Caso seja criado um usuário com username já existente, é retornado um erro\n\n#### Essa rota é liberada a todos\n\n### Retorno esperado\n**STATUS 400 Bad Request**\n```json\n{\n\t\"status\": \"error\",\n\t\"code\": 400,\n\t\"message\": \"Usuário já existe\"\n}\n```","method":"POST","body":{"mimeType":"application/json","text":"{\n\t\"fullname\": \"Bruno Tibério Santinoni\",\n\t\"username\": \"bruno\",\n\t\"password\": \"1234\", \n\t\"emails\": [\"quentemente@gmail.com\", \"brunotiberiosan@gmail.com\"], \n\t\"phones\": [\"61992535393\", \"61993565741\"]\n}"},"parameters":[],"headers":[{"name":"Content-Type","value":"application/json"}],"authentication":{},"metaSortKey":-1669408835070.5,"isPrivate":false,"settingStoreCookies":true,"settingSendCookies":true,"settingDisableRenderRequestBody":false,"settingEncodeUrl":true,"settingRebuildPath":true,"settingFollowRedirects":"global","_type":"request"},{"_id":"req_956b2a2db7c94f81a0752f69ea77ffee","parentId":"fld_05f619cd6e3a4ae08db8c167cdb82bd0","modified":1670496806134,"created":1669923939912,"url":"{{ _.BASE_URL }}/users","name":"Criar usuário - Chaves inválidas","description":"Caso seja criado um usuário sem passar as chaves obrigatórias, é retornado um erro\n\n#### Essa rota é liberada a todos\n\n### Retorno esperado\n**STATUS 400 Bad Request**\n```json\n{\n\t\"status\": \"error\",\n\t\"code\": 400,\n\t\"message\": [\n\t\t\"Nome completo é obrigatório\",\n\t\t\"Username é obrigatório\",\n\t\t\"Senha é obrigatória\",\n\t\t\"Email é obrigatório\",\n\t\t\"Telefone é obrigatório\"\n\t]\n}\n```","method":"POST","body":{"mimeType":"application/json","text":"{}"},"parameters":[],"headers":[{"name":"Content-Type","value":"application/json"}],"authentication":{},"metaSortKey":-1669359452710.25,"isPrivate":false,"settingStoreCookies":true,"settingSendCookies":true,"settingDisableRenderRequestBody":false,"settingEncodeUrl":true,"settingRebuildPath":true,"settingFollowRedirects":"global","_type":"request"},{"_id":"req_b598cce4c6444e3aa1365a91a6c5ae7b","parentId":"fld_05f619cd6e3a4ae08db8c167cdb82bd0","modified":1670495050538,"created":1669905934589,"url":"{{ _.BASE_URL }}/users/{{ _.USER }}","name":"Listar usuário","description":"### Todas as informações devem ser passadas\n- body - não possui corpo na requisição\n- parâmetros - necessário o ID do usuário\n\n**Exemplo:\nbaseUrl/users/198464e1-c0d7-41bf-a2fb-d8129b63e034**\n\n#### Essa rota necessita de autenticação\n\n### Retorno esperado\n**STATUS 200 OK**\n```json\n{\n\t\"createdAt\": \"2022-12-08T09:17:13.783Z\",\n\t\"updatedAt\": \"2022-12-08T09:17:13.783Z\",\n\t\"id\": \"198464e1-c0d7-41bf-a2fb-d8129b63e034\",\n\t\"fullname\": \"Bruno Tibério Santinoni\",\n\t\"username\": \"bruno\",\n\t\"emails\": [\n\t\t\"email1@gmail.com\",\n\t\t\"email2@gmail.com\"\n\t],\n\t\"phones\": [\n\t\t\"61999999999\",\n\t\t\"61955555555\"\n\t],\n\t\"contacts\": []\n}\n```","method":"GET","body":{},"parameters":[],"headers":[],"authentication":{"type":"bearer","token":"{{ _.TOKEN_USER }}","disabled":false},"metaSortKey":-1669310070350,"isPrivate":false,"settingStoreCookies":true,"settingSendCookies":true,"settingDisableRenderRequestBody":false,"settingEncodeUrl":true,"settingRebuildPath":true,"settingFollowRedirects":"global","_type":"request"},{"_id":"req_888dcba9c2ca4b4c8a94c3e65833f994","parentId":"fld_05f619cd6e3a4ae08db8c167cdb82bd0","modified":1670495912828,"created":1669924116794,"url":"{{ _.BASE_URL }}/users/{{ _.USER }}","name":"Listar usuário - Token de outro usuário","description":"Caso tente listar um usuário com o token de outro, um erro é retornado\n\n#### Essa rota necessita de autenticação\n\n### Retorno esperado\n**STATUS 401 Unauthorized**\n```json\n{\n\t\"status\": \"error\",\n\t\"code\": 401,\n\t\"message\": \"Usuário não autorizado\"\n}\n```","method":"GET","body":{},"parameters":[],"headers":[],"authentication":{"type":"bearer","token":"eyJhbGciOiJIUzI1NiIsInR5cCI6IkpXVCJ9.eyJ1c2VySWQiOiIwY2VjM2FmYy1iM2IzLTQxNTgtYTBjZi1iMzhiZGM1MTIzNzEiLCJpYXQiOjE2NzA0OTEzMzQsImV4cCI6MTY3MDQ5NDkzNH0.6hQxpYCrfxKo4HqoZSJ2D6ujahZABv-iWskcxK8nryA"},"metaSortKey":-1669161923269.25,"isPrivate":false,"settingStoreCookies":true,"settingSendCookies":true,"settingDisableRenderRequestBody":false,"settingEncodeUrl":true,"settingRebuildPath":true,"settingFollowRedirects":"global","_type":"request"},{"_id":"req_79591788e7a34a1799fbe7e3e095b303","parentId":"fld_05f619cd6e3a4ae08db8c167cdb82bd0","modified":1670495951621,"created":1669924241579,"url":"{{ _.BASE_URL }}/users/{{ _.USER }}","name":"Listar usuário - Sem token","description":"Caso tente listar um usuário sem um token, um erro é retornado\n\n#### Essa rota necessita de autenticação\n\n### Retorno esperado\n**STATUS 401 Unauthorized**\n```json\n{\n\t\"status\": \"error\",\n\t\"code\": 401,\n\t\"message\": \"Usuário não logado\"\n}\n```","method":"GET","body":{},"parameters":[],"headers":[],"authentication":{"type":"bearer","token":"","disabled":true},"metaSortKey":-1669137232089.125,"isPrivate":false,"settingStoreCookies":true,"settingSendCookies":true,"settingDisableRenderRequestBody":false,"settingEncodeUrl":true,"settingRebuildPath":true,"settingFollowRedirects":"global","_type":"request"},{"_id":"req_1b580b6fb40f4655bb60764e9bbaacd0","parentId":"fld_05f619cd6e3a4ae08db8c167cdb82bd0","modified":1670496120156,"created":1670491462642,"url":"{{ _.BASE_URL }}/users/{{ _.USER }}","name":"Listar usuário - Token inválido","description":"Caso tente listar um usuário com um token inválido, um erro é retornado\n\n#### Essa rota necessita de autenticação\n\n### Retorno esperado\n**STATUS 401 Unauthorized**\n```json\n{\n\t\"status\": \"error\",\n\t\"code\": 401,\n\t\"message\": \"Token inválido\"\n}\n```","method":"GET","body":{},"parameters":[],"headers":[],"authentication":{"type":"bearer","token":"1","disabled":false},"metaSortKey":-1669137232064.125,"isPrivate":false,"settingStoreCookies":true,"settingSendCookies":true,"settingDisableRenderRequestBody":false,"settingEncodeUrl":true,"settingRebuildPath":true,"settingFollowRedirects":"global","_type":"request"},{"_id":"req_27320e6f91a244c8bb2c4b2942668ae2","parentId":"fld_05f619cd6e3a4ae08db8c167cdb82bd0","modified":1670495221645,"created":1669924374940,"url":"{{ _.BASE_URL }}/users/{{ _.USER }}","name":"Atualizar usuário","description":"### Todas as informações devem ser passadas\n- body - pode ser enviado qualquer informação referente ao usuário que deseja atualizar (fullname, username, password, emails e phones)\n- parâmetros - necessário o ID do usuário\n\n**Exemplo:\nbaseUrl/users/198464e1-c0d7-41bf-a2fb-d8129b63e034**\n\n#### Essa rota necessita de autenticação\n\n### Retorno esperado\n**STATUS 200 OK**\n```json\n{\n\t\"createdAt\": \"2022-12-08T09:17:13.783Z\",\n\t\"updatedAt\": \"2022-12-08T09:25:04.046Z\",\n\t\"id\": \"198464e1-c0d7-41bf-a2fb-d8129b63e034\",\n\t\"fullname\": \"Bruno Tibério Santinoni\",\n\t\"username\": \"brunotiberio\",\n\t\"emails\": [\n\t\t\"email1@gmail.com\",\n\t\t\"email2@gmail.com\"\n\t],\n\t\"phones\": [\n\t\t\"61999999999\",\n\t\t\"61955555555\"\n\t],\n\t\"contacts\": []\n}\n```","method":"PATCH","body":{"mimeType":"application/json","text":"{\n\t\"username\": \"brunotiberio\"\n}"},"parameters":[],"headers":[{"name":"Content-Type","value":"application/json","id":"pair_ba597171948a4165917661cb19f0be3f"}],"authentication":{"type":"bearer","token":"{{ _.TOKEN_USER }}"},"metaSortKey":-1669137232039.125,"isPrivate":false,"settingStoreCookies":true,"settingSendCookies":true,"settingDisableRenderRequestBody":false,"settingEncodeUrl":true,"settingRebuildPath":true,"settingFollowRedirects":"global","_type":"request"},{"_id":"req_5bf97d7e7fd745eaa9e84a4f73399b08","parentId":"fld_05f619cd6e3a4ae08db8c167cdb82bd0","modified":1670496332451,"created":1669924624032,"url":"{{ _.BASE_URL }}/users/{{ _.USER }}","name":"Atualizar usuário - Senha igual a anterior","description":"Caso tente atualizar um usuário passando a mesma senha que a anterior, um erro é retornado\n\n#### Essa rota necessita de autenticação\n\n### Retorno esperado\n**STATUS 409 Conflict**\n```json\n{\n\t\"status\": \"error\",\n\t\"code\": 409,\n\t\"message\": \"Informe uma senha diferente\"\n}\n```","method":"PATCH","body":{"mimeType":"application/json","text":"{\n\t\"fullname\": \"Bruno ALTERADO\",\n\t\"username\": \"brunotiberio\",\n\t\"password\": \"1234\", \n\t\"emails\": [\"quentemente@gmail.com\", \"brunotiberiosan@gmail.com\", \"email3@email.com\"], \n\t\"phones\": [\"61992535393\", \"61993565741\", \"61992535396\"]\n}"},"parameters":[],"headers":[{"name":"Content-Type","value":"application/json"}],"authentication":{"type":"bearer","token":"{{ _.TOKEN_USER }}"},"metaSortKey":-1669124886474.0625,"isPrivate":false,"settingStoreCookies":true,"settingSendCookies":true,"settingDisableRenderRequestBody":false,"settingEncodeUrl":true,"settingRebuildPath":true,"settingFollowRedirects":"global","_type":"request"},{"_id":"req_76e993e75e9942629e47cd8c906e9ed8","parentId":"fld_05f619cd6e3a4ae08db8c167cdb82bd0","modified":1670496294127,"created":1669924654868,"url":"{{ _.BASE_URL }}/users/{{ _.USER }}","name":"Atualizar usuário - Token de outro usuário","description":"Caso tente atualizar um usuário com o token de outro, um erro é retornado\n\n#### Essa rota necessita de autenticação\n\n### Retorno esperado\n**STATUS 401 Unauthorized**\n```json\n{\n\t\"status\": \"error\",\n\t\"code\": 401,\n\t\"message\": \"Usuário não autorizado\"\n}\n```","method":"PATCH","body":{"mimeType":"application/json","text":"{\n\t\"fullname\": \"Bruno ALTERADO\",\n\t\"username\": \"bruno\",\n\t\"password\": \"1234\", \n\t\"emails\": [\"quentemente@gmail.com\", \"brunotiberiosan@gmail.com\", \"email3@email.com\"], \n\t\"phones\": [\"61992535393\", \"61993565741\", \"61992535396\"]\n}"},"parameters":[],"headers":[{"name":"Content-Type","value":"application/json"}],"authentication":{"type":"bearer","token":"eyJhbGciOiJIUzI1NiIsInR5cCI6IkpXVCJ9.eyJ1c2VySWQiOiIwY2VjM2FmYy1iM2IzLTQxNTgtYTBjZi1iMzhiZGM1MTIzNzEiLCJpYXQiOjE2NzA0OTEzMzQsImV4cCI6MTY3MDQ5NDkzNH0.6hQxpYCrfxKo4HqoZSJ2D6ujahZABv-iWskcxK8nryA"},"metaSortKey":-1669118713691.5312,"isPrivate":false,"settingStoreCookies":true,"settingSendCookies":true,"settingDisableRenderRequestBody":false,"settingEncodeUrl":true,"settingRebuildPath":true,"settingFollowRedirects":"global","_type":"request"},{"_id":"req_9d3d7447188e428bb48971a19c31e305","parentId":"fld_05f619cd6e3a4ae08db8c167cdb82bd0","modified":1670495990119,"created":1670491636264,"url":"{{ _.BASE_URL }}/users/{{ _.USER }}","name":"Atualizar usuário - Sem token","description":"Caso tente atualizar um usuário sem um token, um erro é retornado\n\n#### Essa rota necessita de autenticação\n\n### Retorno esperado\n**STATUS 401 Unauthorized**\n```json\n{\n\t\"status\": \"error\",\n\t\"code\": 401,\n\t\"message\": \"Usuário não logado\"\n}\n```","method":"PATCH","body":{"mimeType":"application/json","text":"{\n\t\"fullname\": \"Bruno ALTERADO\",\n\t\"username\": \"bruno\",\n\t\"password\": \"1234\", \n\t\"emails\": [\"quentemente@gmail.com\", \"brunotiberiosan@gmail.com\", \"email3@email.com\"], \n\t\"phones\": [\"61992535393\", \"61993565741\", \"61992535396\"]\n}"},"parameters":[],"headers":[{"name":"Content-Type","value":"application/json"}],"authentication":{"type":"bearer","token":"eyJhbGciOiJIUzI1NiIsInR5cCI6IkpXVCJ9.eyJ1c2VySWQiOiIwY2VjM2FmYy1iM2IzLTQxNTgtYTBjZi1iMzhiZGM1MTIzNzEiLCJpYXQiOjE2NzA0OTEzMzQsImV4cCI6MTY3MDQ5NDkzNH0.6hQxpYCrfxKo4HqoZSJ2D6ujahZABv-iWskcxK8nryA","disabled":true},"metaSortKey":-1669117170495.8984,"isPrivate":false,"settingStoreCookies":true,"settingSendCookies":true,"settingDisableRenderRequestBody":false,"settingEncodeUrl":true,"settingRebuildPath":true,"settingFollowRedirects":"global","_type":"request"},{"_id":"req_3012ee737634491ea682eb0cacdb9b5c","parentId":"fld_05f619cd6e3a4ae08db8c167cdb82bd0","modified":1670496132553,"created":1670491659545,"url":"{{ _.BASE_URL }}/users/{{ _.USER }}","name":"Atualizar usuário - Token inválido","description":"Caso tente atualizar um usuário com um token inválido, um erro é retornado\n\n#### Essa rota necessita de autenticação\n\n### Retorno esperado\n**STATUS 401 Unauthorized**\n```json\n{\n\t\"status\": \"error\",\n\t\"code\": 401,\n\t\"message\": \"Token inválido\"\n}\n```","method":"PATCH","body":{"mimeType":"application/json","text":"{\n\t\"fullname\": \"Bruno ALTERADO\",\n\t\"username\": \"bruno\",\n\t\"password\": \"1234\", \n\t\"emails\": [\"quentemente@gmail.com\", \"brunotiberiosan@gmail.com\", \"email3@email.com\"], \n\t\"phones\": [\"61992535393\", \"61993565741\", \"61992535396\"]\n}"},"parameters":[],"headers":[{"name":"Content-Type","value":"application/json"}],"authentication":{"type":"bearer","token":"1","disabled":false},"metaSortKey":-1669116398898.082,"isPrivate":false,"settingStoreCookies":true,"settingSendCookies":true,"settingDisableRenderRequestBody":false,"settingEncodeUrl":true,"settingRebuildPath":true,"settingFollowRedirects":"global","_type":"request"},{"_id":"req_19818276ec584c3d90d8ae4cfc405a5a","parentId":"fld_05f619cd6e3a4ae08db8c167cdb82bd0","modified":1670496785343,"created":1669924677111,"url":"{{ _.BASE_URL }}/users/{{ _.USER }}","name":"Deletar usuário","description":"### Todas as informações devem ser passadas\n- body - não é necessário\n- parâmetros - necessário o ID do usuário\n\n**Exemplo:\nbaseUrl/users/198464e1-c0d7-41bf-a2fb-d8129b63e034**\n\n#### Essa rota necessita de autenticação\n\n### Retorno esperado\n**STATUS 204 No Content**\n```json\nNo body returned for response\n```","method":"DELETE","body":{},"parameters":[],"headers":[],"authentication":{"type":"bearer","token":"{{ _.TOKEN_USER }}"},"metaSortKey":-1669115627300.2656,"isPrivate":false,"settingStoreCookies":true,"settingSendCookies":true,"settingDisableRenderRequestBody":false,"settingEncodeUrl":true,"settingRebuildPath":true,"settingFollowRedirects":"global","_type":"request"},{"_id":"req_5d7012f5300c45c98d189bb7745ed1b5","parentId":"fld_05f619cd6e3a4ae08db8c167cdb82bd0","modified":1670495789592,"created":1670491725580,"url":"{{ _.BASE_URL }}/users/{{ _.USER }}","name":"Deletar usuário - Token de outro usuário","description":"Caso tente deletar um usuário com o token de outro, um erro é retornado\n\n#### Essa rota necessita de autenticação\n\n### Retorno esperado\n**STATUS 401 Unauthorized**\n```json\n{\n\t\"status\": \"error\",\n\t\"code\": 401,\n\t\"message\": \"Usuário não autorizado\"\n}\n```","method":"DELETE","body":{},"parameters":[],"headers":[],"authentication":{"type":"bearer","token":"eyJhbGciOiJIUzI1NiIsInR5cCI6IkpXVCJ9.eyJ1c2VySWQiOiIwY2VjM2FmYy1iM2IzLTQxNTgtYTBjZi1iMzhiZGM1MTIzNzEiLCJpYXQiOjE2NzA0OTEzMzQsImV4cCI6MTY3MDQ5NDkzNH0.6hQxpYCrfxKo4HqoZSJ2D6ujahZABv-iWskcxK8nryA"},"metaSortKey":-1669114084104.6328,"isPrivate":false,"settingStoreCookies":true,"settingSendCookies":true,"settingDisableRenderRequestBody":false,"settingEncodeUrl":true,"settingRebuildPath":true,"settingFollowRedirects":"global","_type":"request"},{"_id":"req_c61ee181f602453882ff29a58d993501","parentId":"fld_05f619cd6e3a4ae08db8c167cdb82bd0","modified":1670495966568,"created":1670491759042,"url":"{{ _.BASE_URL }}/users/{{ _.USER }}","name":"Deletar usuário - Sem token","description":"Caso tente deletar um usuário sem um token, um erro é retornado\n\n#### Essa rota necessita de autenticação\n\n### Retorno esperado\n**STATUS 401 Unauthorized**\n```json\n{\n\t\"status\": \"error\",\n\t\"code\": 401,\n\t\"message\": \"Usuário não logado\"\n}\n```","method":"DELETE","body":{},"parameters":[],"headers":[],"authentication":{"type":"bearer","token":"","disabled":true},"metaSortKey":-1669113312506.8164,"isPrivate":false,"settingStoreCookies":true,"settingSendCookies":true,"settingDisableRenderRequestBody":false,"settingEncodeUrl":true,"settingRebuildPath":true,"settingFollowRedirects":"global","_type":"request"},{"_id":"req_0e8eba5f82e949e2827dfefe43495ecb","parentId":"fld_05f619cd6e3a4ae08db8c167cdb82bd0","modified":1670496150124,"created":1670491786671,"url":"{{ _.BASE_URL }}/users/{{ _.USER }}","name":"Deletar usuário - Token inválido","description":"Caso tente listar um usuário com um token inválido, um erro é retornado\n\n#### Essa rota necessita de autenticação\n\n### Retorno esperado\n**STATUS 401 Unauthorized**\n```json\n{\n\t\"status\": \"error\",\n\t\"code\": 401,\n\t\"message\": \"Token inválido\"\n}\n```","method":"DELETE","body":{},"parameters":[],"headers":[],"authentication":{"type":"bearer","token":"1","disabled":false},"metaSortKey":-1669112926707.9082,"isPrivate":false,"settingStoreCookies":true,"settingSendCookies":true,"settingDisableRenderRequestBody":false,"settingEncodeUrl":true,"settingRebuildPath":true,"settingFollowRedirects":"global","_type":"request"},{"_id":"req_898106e5716240debe15cb64fd1c4b3f","parentId":"fld_069c821f6c89426eb3bead9b3269f20a","modified":1670496791425,"created":1669902658673,"url":"{{ _.BASE_URL }}/login","name":"Login de usuário","description":"### Todos os campos de envio são obrigatórios\n- username - deve ser do tipo string\n- password - deve ser do tipo string\n\n#### Essa rota é liberada a todos\n\n### Retorno esperado\n**STATUS 20 OK**\n```json\n{\n\t\"id\": \"198464e1-c0d7-41bf-a2fb-d8129b63e034\",\n\t\"token\": \"eyJhbGciOiJIUzI1NiIsInR5cCI6IkpXVCJ9.eyJ1c2VySWQiOiIxOTg0NjRlMS1jMGQ3LTQxYmYtYTJmYi1kODEyOWI2M2UwMzQiLCJpYXQiOjE2NzA0OTEyMTgsImV4cCI6MTY3MDQ5NDgxOH0.Le1MB3_wzu6czR0EeznxWfXgwJmdUGeuuyk-ni8StvQ\"\n}\n```","method":"POST","body":{"mimeType":"application/json","text":"{\n\t\"username\": \"bruno\",\n\t\"password\": \"1234\"\n}"},"parameters":[],"headers":[{"name":"Content-Type","value":"application/json"}],"authentication":{},"metaSortKey":-1669902658673,"isPrivate":false,"settingStoreCookies":true,"settingSendCookies":true,"settingDisableRenderRequestBody":false,"settingEncodeUrl":true,"settingRebuildPath":true,"settingFollowRedirects":"global","_type":"request"},{"_id":"fld_069c821f6c89426eb3bead9b3269f20a","parentId":"wrk_fe269e2b2b2f4b49a48b1a140f511443","modified":1670493548944,"created":1669904963990,"name":"Login","description":"<p>Rota responsável pela autenticação do usuário no sistema, importantíssimo para boa tarde das ações realizadas pelo usuário</p>","environment":{},"environmentPropertyOrder":null,"metaSortKey":-1669902687455,"_type":"request_group"},{"_id":"req_5f68b2ff01dc4f7b830b51cf558c01cf","parentId":"fld_069c821f6c89426eb3bead9b3269f20a","modified":1670496920546,"created":1670491841674,"url":"{{ _.BASE_URL }}/login","name":"Login de usuário - Chaves inválidas","description":"Caso tente logar um usuário sem passar as chaves obrigatórias, é retornado um erro\n\n#### Essa rota é liberada a todos\n\n### Retorno esperado\n**STATUS 400 Bad Request**\n```json\n{\n\t\"status\": \"error\",\n\t\"code\": 400,\n\t\"message\": [\n\t\t\"Username é obrigatório\",\n\t\t\"Senha é obrigatória\"\n\t]\n}\n```","method":"POST","body":{"mimeType":"application/json","text":"{}"},"parameters":[],"headers":[{"name":"Content-Type","value":"application/json"}],"authentication":{},"metaSortKey":-1669853276312.75,"isPrivate":false,"settingStoreCookies":true,"settingSendCookies":true,"settingDisableRenderRequestBody":false,"settingEncodeUrl":true,"settingRebuildPath":true,"settingFollowRedirects":"global","_type":"request"},{"_id":"req_9118c88403d747ad9a466918a40ead60","parentId":"fld_069c821f6c89426eb3bead9b3269f20a","modified":1670496975361,"created":1670491870321,"url":"{{ _.BASE_URL }}/login","name":"Login de usuário - Erro de credenciais","description":"Caso tente logar um usuário enviando as credenciais de login incorretas, é retornado um erro\n\n#### Essa rota é liberada a todos\n\n### Retorno esperado\n**STATUS 403 Forbidden**\n```json\n{\n\t\"status\": \"error\",\n\t\"code\": 403,\n\t\"message\": \"Username ou senha inválidos\"\n}\n```","method":"POST","body":{"mimeType":"application/json","text":"{\n\t\"username\": \"usernameInexistente\",\n\t\"password\": \"senhaForte\"\n}"},"parameters":[],"headers":[{"name":"Content-Type","value":"application/json"}],"authentication":{},"metaSortKey":-1669828585132.625,"isPrivate":false,"settingStoreCookies":true,"settingSendCookies":true,"settingDisableRenderRequestBody":false,"settingEncodeUrl":true,"settingRebuildPath":true,"settingFollowRedirects":"global","_type":"request"},{"_id":"req_0d31f012aa6b46e894779df24cfffd8f","parentId":"fld_801c2b912ab44b7ca0b62e075c442527","modified":1670495025599,"created":1669981533063,"url":"{{ _.BASE_URL }}/contacts","name":"Criar contato","description":"### Todos os campos de envio são obrigatórios\n- fullname - deve ser do tipo string\n- emails - deve ser um array de strings\n- phones - deve ser um array de strings\n\n#### Essa rota necessita de autenticação\n\n### Retorno esperado\n**STATUS 201 Created**\n```json\n{\n\t\"id\": \"057946cc-d701-4aee-9b5c-704060ec10cf\",\n\t\"fullname\": \"Bruno Contato\",\n\t\"emails\": [\n\t\t\"email@gmail.com\",\n\t\t\"email@gmail.com\",\n\t\t\"email@gmail.com\",\n\t\t\"email@gmail.com\"\n\t],\n\t\"phones\": [\n\t\t\"61993565742\",\n\t\t\"61993565743\",\n\t\t\"61993565745\",\n\t\t\"61993565744\"\n\t]\n}\n```","method":"POST","body":{"mimeType":"application/json","text":"{\n\t\"fullname\": \"Bruno Contato\",\n  \"emails\": [\"email@gmail.com\", \"email@gmail.com\", \"email@gmail.com\", \"email@gmail.com\"],\n  \"phones\": [\"61993565742\", \"61993565743\", \"61993565745\", \"61993565744\"]\n}"},"parameters":[],"headers":[{"name":"Content-Type","value":"application/json","id":"pair_4a1e90f88b6a49dc8eebd26557c0798c"}],"authentication":{"type":"bearer","token":"{{ _.TOKEN_USER }}"},"metaSortKey":-1669981533063,"isPrivate":false,"settingStoreCookies":true,"settingSendCookies":true,"settingDisableRenderRequestBody":false,"settingEncodeUrl":true,"settingRebuildPath":true,"settingFollowRedirects":"global","_type":"request"},{"_id":"fld_801c2b912ab44b7ca0b62e075c442527","parentId":"wrk_fe269e2b2b2f4b49a48b1a140f511443","modified":1670493591598,"created":1669902687430,"name":"Contatos","description":"<p>Rota de criação, atualização, listagem e deleção de usuários. Para funcionarem, é importante estar logado.</p>","environment":{},"environmentPropertyOrder":null,"metaSortKey":-1669902687430,"_type":"request_group"},{"_id":"req_9676be45db4149928e6760f04c6d9855","parentId":"fld_801c2b912ab44b7ca0b62e075c442527","modified":1670496400548,"created":1670491955470,"url":"{{ _.BASE_URL }}/contacts","name":"Criar contato - Chaves inválidas","description":"Caso seja criado um contato sem passar as chaves obrigatórias, é retornado um erro\n\n#### Essa rota necessita de autenticação\n\n### Retorno esperado\n**STATUS 400 Bad Request**\n```json\n{\n\t\"status\": \"error\",\n\t\"code\": 400,\n\t\"message\": [\n\t\t\"Nome completo é obrigatório\",\n\t\t\"Email é obrigatório\",\n\t\t\"Telefone é obrigatório\"\n\t]\n}\n```","method":"POST","body":{"mimeType":"application/json","text":"{}"},"parameters":[],"headers":[{"name":"Content-Type","value":"application/json","id":"pair_4a1e90f88b6a49dc8eebd26557c0798c"}],"authentication":{"type":"bearer","token":"{{ _.TOKEN_USER }}"},"metaSortKey":-1669961814465.5,"isPrivate":false,"settingStoreCookies":true,"settingSendCookies":true,"settingDisableRenderRequestBody":false,"settingEncodeUrl":true,"settingRebuildPath":true,"settingFollowRedirects":"global","_type":"request"},{"_id":"req_c85fed1644c143e5b025c3616fbb51cd","parentId":"fld_801c2b912ab44b7ca0b62e075c442527","modified":1670496422893,"created":1670491982266,"url":"{{ _.BASE_URL }}/contacts","name":"Criar contato - Sem token","description":"Caso tente criar um contato sem um token, um erro é retornado\n\n#### Essa rota necessita de autenticação\n\n### Retorno esperado\n**STATUS 401 Unauthorized**\n```json\n{\n\t\"status\": \"error\",\n\t\"code\": 401,\n\t\"message\": \"Usuário não logado\"\n}\n```","method":"POST","body":{"mimeType":"application/json","text":"{\n\t\"fullname\": \"Bruno 4\",\n  \"emails\": [\"email@gmail.com\", \"email@gmail.com\", \"email@gmail.com\", \"email@gmail.com\"],\n  \"phones\": [\"61993565742\", \"61993565743\", \"61993565744\", \"61993565745\"]\n}"},"parameters":[],"headers":[{"name":"Content-Type","value":"application/json","id":"pair_4a1e90f88b6a49dc8eebd26557c0798c"}],"authentication":{"type":"bearer","token":"","disabled":true},"metaSortKey":-1669951955166.75,"isPrivate":false,"settingStoreCookies":true,"settingSendCookies":true,"settingDisableRenderRequestBody":false,"settingEncodeUrl":true,"settingRebuildPath":true,"settingFollowRedirects":"global","_type":"request"},{"_id":"req_d67b4d8082e74cf8b85845cbda2de542","parentId":"fld_801c2b912ab44b7ca0b62e075c442527","modified":1670496180386,"created":1670492059839,"url":"{{ _.BASE_URL }}/contacts","name":"Criar contato - Token inválido","description":"Caso tente criar um contato com um token inválido, um erro é retornado\n\n#### Essa rota necessita de autenticação\n\n### Retorno esperado\n**STATUS 401 Unauthorized**\n```json\n{\n\t\"status\": \"error\",\n\t\"code\": 401,\n\t\"message\": \"Token inválido\"\n}\n```","method":"POST","body":{"mimeType":"application/json","text":"{\n\t\"fullname\": \"Bruno 4\",\n  \"emails\": [\"email@gmail.com\", \"email@gmail.com\", \"email@gmail.com\", \"email@gmail.com\"],\n  \"phones\": [\"61993565742\", \"61993565743\", \"61993565744\", \"61993565745\"]\n}"},"parameters":[],"headers":[{"name":"Content-Type","value":"application/json","id":"pair_4a1e90f88b6a49dc8eebd26557c0798c"}],"authentication":{"type":"bearer","token":"1","disabled":false},"metaSortKey":-1669947025517.375,"isPrivate":false,"settingStoreCookies":true,"settingSendCookies":true,"settingDisableRenderRequestBody":false,"settingEncodeUrl":true,"settingRebuildPath":true,"settingFollowRedirects":"global","_type":"request"},{"_id":"req_fd70bddbb1fd4a94950e2ae9573abd4a","parentId":"fld_801c2b912ab44b7ca0b62e075c442527","modified":1670495145312,"created":1669982136582,"url":"{{ _.BASE_URL }}/contacts/{{ _.CONTACT_ID }}","name":"Listar contato por ID","description":"### Todas as informações devem ser passadas\n- body - não possui corpo na requisição\n- parâmetros - necessário o ID do contato\n\n**Exemplo:\nbaseUrl/contacts/198464e1-c0d7-41bf-a2fb-d8129b63e034**\n\n#### Essa rota necessita de autenticação\n\n### Retorno esperado\n**STATUS 200 OK**\n```json\n{\n\t\"id\": \"057946cc-d701-4aee-9b5c-704060ec10cf\",\n\t\"fullname\": \"Bruno Contato\",\n\t\"emails\": [\n\t\t\"email@gmail.com\",\n\t\t\"email@gmail.com\",\n\t\t\"email@gmail.com\",\n\t\t\"email@gmail.com\"\n\t],\n\t\"phones\": [\n\t\t\"61993565742\",\n\t\t\"61993565743\",\n\t\t\"61993565745\",\n\t\t\"61993565744\"\n\t]\n}\n```","method":"GET","body":{"mimeType":"application/json","text":""},"parameters":[],"headers":[{"name":"Content-Type","value":"application/json"}],"authentication":{"type":"bearer","token":"{{ _.TOKEN_USER }}","disabled":false},"metaSortKey":-1669942095868,"isPrivate":false,"settingStoreCookies":true,"settingSendCookies":true,"settingDisableRenderRequestBody":false,"settingEncodeUrl":true,"settingRebuildPath":true,"settingFollowRedirects":"global","_type":"request"},{"_id":"req_532c0a3ad57d4a4c862713eb91f622a7","parentId":"fld_801c2b912ab44b7ca0b62e075c442527","modified":1670496486189,"created":1670492343102,"url":"{{ _.BASE_URL }}/contacts/{{ _.CONTACT_ID }}","name":"Listar contato por ID - Sem Token","description":"Caso tente listar um contato sem um token, um erro é retornado\n\n#### Essa rota necessita de autenticação\n\n### Retorno esperado\n**STATUS 401 Unauthorized**\n```json\n{\n\t\"status\": \"error\",\n\t\"code\": 401,\n\t\"message\": \"Usuário não logado\"\n}\n```","method":"GET","body":{"mimeType":"application/json","text":""},"parameters":[],"headers":[{"name":"Content-Type","value":"application/json"}],"authentication":{"type":"bearer","token":"","disabled":true},"metaSortKey":-1669932236569.25,"isPrivate":false,"settingStoreCookies":true,"settingSendCookies":true,"settingDisableRenderRequestBody":false,"settingEncodeUrl":true,"settingRebuildPath":true,"settingFollowRedirects":"global","_type":"request"},{"_id":"req_0606fb91d7b04c4baf293853e180bdc6","parentId":"fld_801c2b912ab44b7ca0b62e075c442527","modified":1670496205680,"created":1670492412722,"url":"{{ _.BASE_URL }}/contacts/{{ _.CONTACT_ID }}","name":"Listar contato por ID - Token inválido","description":"Caso tente listar um contato com um token inválido, um erro é retornado\n\n#### Essa rota necessita de autenticação\n\n### Retorno esperado\n**STATUS 401 Unauthorized**\n```json\n{\n\t\"status\": \"error\",\n\t\"code\": 401,\n\t\"message\": \"Token inválido\"\n}\n```","method":"GET","body":{"mimeType":"application/json","text":""},"parameters":[],"headers":[{"name":"Content-Type","value":"application/json"}],"authentication":{"type":"bearer","token":"1","disabled":false},"metaSortKey":-1669927306919.875,"isPrivate":false,"settingStoreCookies":true,"settingSendCookies":true,"settingDisableRenderRequestBody":false,"settingEncodeUrl":true,"settingRebuildPath":true,"settingFollowRedirects":"global","_type":"request"},{"_id":"req_eaa019722a92458bbcf040222adc0367","parentId":"fld_801c2b912ab44b7ca0b62e075c442527","modified":1670495188595,"created":1669982773254,"url":"{{ _.BASE_URL }}/contacts/user/{{ _.USER }}","name":"Listar contatos por usuário","description":"### Todas as informações devem ser passadas\n- body - não possui corpo na requisição\n- parâmetros - necessário o ID do usuário\n\n**Exemplo:\nbaseUrl/contacts/user/198464e1-c0d7-41bf-a2fb-d8129b63e034**\n\n#### Essa rota necessita de autenticação\n\n### Retorno esperado\n**STATUS 200 OK**\n```json\n{\n\t\"id\": \"057946cc-d701-4aee-9b5c-704060ec10cf\",\n\t\"fullname\": \"Bruno Contato\",\n\t\"emails\": [\n\t\t\"email@gmail.com\",\n\t\t\"email@gmail.com\",\n\t\t\"email@gmail.com\",\n\t\t\"email@gmail.com\"\n\t],\n\t\"phones\": [\n\t\t\"61993565742\",\n\t\t\"61993565743\",\n\t\t\"61993565745\",\n\t\t\"61993565744\"\n\t]\n}\n```","method":"GET","body":{"mimeType":"application/json","text":""},"parameters":[],"headers":[{"name":"Content-Type","value":"application/json"}],"authentication":{"type":"bearer","token":"{{ _.TOKEN_USER }}","disabled":false},"metaSortKey":-1669922377270.5,"isPrivate":false,"settingStoreCookies":true,"settingSendCookies":true,"settingDisableRenderRequestBody":false,"settingEncodeUrl":true,"settingRebuildPath":true,"settingFollowRedirects":"global","_type":"request"},{"_id":"req_8c8401ec668c4f209401c301c6efab74","parentId":"fld_801c2b912ab44b7ca0b62e075c442527","modified":1670496583017,"created":1670492504331,"url":"{{ _.BASE_URL }}/contacts/user/{{ _.USER }}","name":"Listar contatos por usuário - Sem token","description":"Caso tente listar os contatos de um usuário sem um token, um erro é retornado\n\n#### Essa rota necessita de autenticação\n\n### Retorno esperado\n**STATUS 401 Unauthorized**\n```json\n{\n\t\"status\": \"error\",\n\t\"code\": 401,\n\t\"message\": \"Usuário não logado\"\n}\n```","method":"GET","body":{"mimeType":"application/json","text":""},"parameters":[],"headers":[{"name":"Content-Type","value":"application/json"}],"authentication":{"type":"bearer","token":"","disabled":true},"metaSortKey":-1669922377245.5,"isPrivate":false,"settingStoreCookies":true,"settingSendCookies":true,"settingDisableRenderRequestBody":false,"settingEncodeUrl":true,"settingRebuildPath":true,"settingFollowRedirects":"global","_type":"request"},{"_id":"req_4d4647af1d0e489e904b051026241031","parentId":"fld_801c2b912ab44b7ca0b62e075c442527","modified":1670496218381,"created":1670492526486,"url":"{{ _.BASE_URL }}/contacts/user/{{ _.USER }}","name":"Listar contatos por usuário - Token inválido","description":"Caso tente listar um contato com um token inválido, um erro é retornado\n\n#### Essa rota necessita de autenticação\n\n### Retorno esperado\n**STATUS 401 Unauthorized**\n```json\n{\n\t\"status\": \"error\",\n\t\"code\": 401,\n\t\"message\": \"Token inválido\"\n}\n```","method":"GET","body":{"mimeType":"application/json","text":""},"parameters":[],"headers":[{"name":"Content-Type","value":"application/json"}],"authentication":{"type":"bearer","token":"1","disabled":false},"metaSortKey":-1669922377233,"isPrivate":false,"settingStoreCookies":true,"settingSendCookies":true,"settingDisableRenderRequestBody":false,"settingEncodeUrl":true,"settingRebuildPath":true,"settingFollowRedirects":"global","_type":"request"},{"_id":"req_d70aaf5b3db14780a65d235d648ca7fc","parentId":"fld_801c2b912ab44b7ca0b62e075c442527","modified":1670495305477,"created":1669983509422,"url":"{{ _.BASE_URL }}/contacts/{{ _.CONTACT_ID }}","name":"Atualizar contato por ID","description":"### Todas as informações devem ser passadas\n- body - pode ser enviado qualquer informação referente ao contato que deseja atualizar (fullname, emails e phones)\n- parâmetros - necessário o ID do contato\n\n**Exemplo:\nbaseUrl/contacts/198464e1-c0d7-41bf-a2fb-d8129b63e034**\n\n#### Essa rota necessita de autenticação\n\n### Retorno esperado\n**STATUS 200 OK**\n```json\n{\n\t\"id\": \"057946cc-d701-4aee-9b5c-704060ec10cf\",\n\t\"fullname\": \"Lucimeire ALTERADO\",\n\t\"emails\": [\n\t\t\"email@gmail.com\",\n\t\t\"email@gmail.com\",\n\t\t\"email@gmail.com\",\n\t\t\"email@gmail.com\"\n\t],\n\t\"phones\": [\n\t\t\"61993565742\",\n\t\t\"61993565743\",\n\t\t\"61993565745\",\n\t\t\"61993565744\"\n\t]\n}\n```","method":"PATCH","body":{"mimeType":"application/json","text":"{\n\t\"fullname\": \"Lucimeire ALTERADO\"\n}"},"parameters":[],"headers":[{"name":"Content-Type","value":"application/json"}],"authentication":{"type":"bearer","token":"{{ _.TOKEN_USER }}","disabled":false},"metaSortKey":-1669922377220.5,"isPrivate":false,"settingStoreCookies":true,"settingSendCookies":true,"settingDisableRenderRequestBody":false,"settingEncodeUrl":true,"settingRebuildPath":true,"settingFollowRedirects":"global","_type":"request"},{"_id":"req_1ad249e2403a4228829b1b841ba4feaa","parentId":"fld_801c2b912ab44b7ca0b62e075c442527","modified":1670496659602,"created":1670492744618,"url":"{{ _.BASE_URL }}/contacts/1","name":"Atualizar contato por ID - ID inválida","description":"Caso tente atualizar um contato passando uma ID inválida, um erro é retornado\n\n#### Essa rota necessita de autenticação\n\n### Retorno esperado\n**STATUS 500 Internal Server Error**\n```json\n{\n\t\"status\": \"error\",\n\t\"code\": 500,\n\t\"message\": \"Erro interno no servidor\"\n}\n```","method":"PATCH","body":{"mimeType":"application/json","text":"{\n\t\"fullname\": \"Lucimeire ALTERADO\"\n}"},"parameters":[],"headers":[{"name":"Content-Type","value":"application/json"}],"authentication":{"type":"bearer","token":"{{ _.TOKEN_USER }}","disabled":false},"metaSortKey":-1669919912402.0625,"isPrivate":false,"settingStoreCookies":true,"settingSendCookies":true,"settingDisableRenderRequestBody":false,"settingEncodeUrl":true,"settingRebuildPath":true,"settingFollowRedirects":"global","_type":"request"},{"_id":"req_5149ab7a820546b392a33b22f74645a5","parentId":"fld_801c2b912ab44b7ca0b62e075c442527","modified":1670496067432,"created":1670492634250,"url":"{{ _.BASE_URL }}/contacts/{{ _.CONTACT_ID }}","name":"Atualizar contato por ID - Sem token","description":"Caso tente atualizar um contato sem um token, um erro é retornado\n\n#### Essa rota necessita de autenticação\n\n### Retorno esperado\n**STATUS 401 Unauthorized**\n```json\n{\n\t\"status\": \"error\",\n\t\"code\": 401,\n\t\"message\": \"Usuário não logado\"\n}\n```","method":"PATCH","body":{"mimeType":"application/json","text":"{\n\t\"fullname\": \"Lucimeire ALTERADO\"\n}"},"parameters":[],"headers":[{"name":"Content-Type","value":"application/json"}],"authentication":{"type":"bearer","token":"","disabled":true},"metaSortKey":-1669917447583.625,"isPrivate":false,"settingStoreCookies":true,"settingSendCookies":true,"settingDisableRenderRequestBody":false,"settingEncodeUrl":true,"settingRebuildPath":true,"settingFollowRedirects":"global","_type":"request"},{"_id":"req_ab789476623a4d2295ac4981913b42fe","parentId":"fld_801c2b912ab44b7ca0b62e075c442527","modified":1670496231836,"created":1670492644530,"url":"{{ _.BASE_URL }}/contacts/{{ _.CONTACT_ID }}","name":"Atualizar contato por ID - Token inválido","description":"Caso tente atualizar um contato com um token inválido, um erro é retornado\n\n#### Essa rota necessita de autenticação\n\n### Retorno esperado\n**STATUS 401 Unauthorized**\n```json\n{\n\t\"status\": \"error\",\n\t\"code\": 401,\n\t\"message\": \"Token inválido\"\n}\n```","method":"PATCH","body":{"mimeType":"application/json","text":"{\n\t\"fullname\": \"Lucimeire ALTERADO\"\n}"},"parameters":[],"headers":[{"name":"Content-Type","value":"application/json"}],"authentication":{"type":"bearer","token":"1","disabled":false},"metaSortKey":-1669914982765.1875,"isPrivate":false,"settingStoreCookies":true,"settingSendCookies":true,"settingDisableRenderRequestBody":false,"settingEncodeUrl":true,"settingRebuildPath":true,"settingFollowRedirects":"global","_type":"request"},{"_id":"req_46b6cc8a34f544d4a00d40610712a635","parentId":"fld_801c2b912ab44b7ca0b62e075c442527","modified":1670495342174,"created":1669984189501,"url":"{{ _.BASE_URL }}/contacts/{{ _.CONTACT_ID }}","name":"Deletar contato por ID","description":"### Todas as informações devem ser passadas\n- body - não é necessário\n- parâmetros - necessário o ID do usuário\n\n**Exemplo:\nbaseUrl/contacts/198464e1-c0d7-41bf-a2fb-d8129b63e034**\n\n#### Essa rota necessita de autenticação\n\n### Retorno esperado\n**STATUS 204 No Content**\n```json\nNo body returned for response\n```","method":"DELETE","body":{},"parameters":[],"headers":[],"authentication":{"type":"bearer","token":"{{ _.TOKEN_USER }}","disabled":false},"metaSortKey":-1669912517946.75,"isPrivate":false,"settingStoreCookies":true,"settingSendCookies":true,"settingDisableRenderRequestBody":false,"settingEncodeUrl":true,"settingRebuildPath":true,"settingFollowRedirects":"global","_type":"request"},{"_id":"req_6da3acd118d749518bfe3a1dcc56d277","parentId":"fld_801c2b912ab44b7ca0b62e075c442527","modified":1670496670504,"created":1670492804814,"url":"{{ _.BASE_URL }}/contacts/1","name":"Deletar contato por ID - ID inválida","description":"Caso tente deletar um contato passando uma ID inválida, um erro é retornado\n\n#### Essa rota necessita de autenticação\n\n### Retorno esperado\n**STATUS 500 Internal Server Error**\n```json\n{\n\t\"status\": \"error\",\n\t\"code\": 500,\n\t\"message\": \"Erro interno no servidor\"\n}\n```","method":"DELETE","body":{},"parameters":[],"headers":[],"authentication":{"type":"bearer","token":"{{ _.TOKEN_USER }}","disabled":false},"metaSortKey":-1669907588309.875,"isPrivate":false,"settingStoreCookies":true,"settingSendCookies":true,"settingDisableRenderRequestBody":false,"settingEncodeUrl":true,"settingRebuildPath":true,"settingFollowRedirects":"global","_type":"request"},{"_id":"req_cdacff7770274d5a9b40250d632e727c","parentId":"fld_801c2b912ab44b7ca0b62e075c442527","modified":1670496083659,"created":1670492828770,"url":"{{ _.BASE_URL }}/contacts/{{ _.CONTACT_ID }}","name":"Deletar contato por ID - Sem token","description":"Caso tente deletar um contato sem um token, um erro é retornado\n\n#### Essa rota necessita de autenticação\n\n### Retorno esperado\n**STATUS 401 Unauthorized**\n```json\n{\n\t\"status\": \"error\",\n\t\"code\": 401,\n\t\"message\": \"Usuário não logado\"\n}\n```","method":"DELETE","body":{},"parameters":[],"headers":[],"authentication":{"type":"bearer","token":"","disabled":true},"metaSortKey":-1669907588259.875,"isPrivate":false,"settingStoreCookies":true,"settingSendCookies":true,"settingDisableRenderRequestBody":false,"settingEncodeUrl":true,"settingRebuildPath":true,"settingFollowRedirects":"global","_type":"request"},{"_id":"req_efa715778a844fd1a8592828e0e8285e","parentId":"fld_801c2b912ab44b7ca0b62e075c442527","modified":1670496242318,"created":1670492845838,"url":"{{ _.BASE_URL }}/contacts/{{ _.CONTACT_ID }}","name":"Deletar contato por ID - Token inválido","description":"Caso tente deletar um contato com um token inválido, um erro é retornado\n\n#### Essa rota necessita de autenticação\n\n### Retorno esperado\n**STATUS 401 Unauthorized**\n```json\n{\n\t\"status\": \"error\",\n\t\"code\": 401,\n\t\"message\": \"Token inválido\"\n}\n```","method":"DELETE","body":{},"parameters":[],"headers":[],"authentication":{"type":"bearer","token":"1","disabled":false},"metaSortKey":-1669907588209.875,"isPrivate":false,"settingStoreCookies":true,"settingSendCookies":true,"settingDisableRenderRequestBody":false,"settingEncodeUrl":true,"settingRebuildPath":true,"settingFollowRedirects":"global","_type":"request"},{"_id":"env_6c14a8085212b22d0943435e2a0a9ff6bcc6d839","parentId":"wrk_fe269e2b2b2f4b49a48b1a140f511443","modified":1670493633275,"created":1669902565634,"name":"Base Environment","data":{"BASE_URL":"http://localhost:4000","USER":"{% response 'body', 'req_898106e5716240debe15cb64fd1c4b3f', 'b64::JC5pZA==::46b', 'never', 60 %}","TOKEN_USER":"{% response 'body', 'req_898106e5716240debe15cb64fd1c4b3f', 'b64::JC50b2tlbg==::46b', 'never', 60 %}","CONTACT_ID":"{% response 'body', 'req_0d31f012aa6b46e894779df24cfffd8f', 'b64::JC5pZA==::46b', 'never', 60 %}"},"dataPropertyOrder":{"&":["BASE_URL","USER","TOKEN_USER","CONTACT_ID"]},"color":null,"isPrivate":false,"metaSortKey":1669902565634,"_type":"environment"},{"_id":"jar_6c14a8085212b22d0943435e2a0a9ff6bcc6d839","parentId":"wrk_fe269e2b2b2f4b49a48b1a140f511443","modified":1669902565637,"created":1669902565637,"name":"Default Jar","cookies":[],"_type":"cookie_jar"},{"_id":"spc_97f0407aa6754979bde1316301759cd9","parentId":"wrk_fe269e2b2b2f4b49a48b1a140f511443","modified":1669902565625,"created":1669902565625,"fileName":"M6-Fullstack-S3","contents":"","contentType":"yaml","_type":"api_spec"}]}